snackcache/__init__.py
snackcache/cache.py
snackcache/cli.py
snackcache/main.py
snackcache/normalizer.py
snackcache/proxy.py
snackcache-0.2.0.dist-info/licenses/LICENSE
snackcache-0.2.0.dist-info/METADATA
snackcache-0.2.0.dist-info/WHEEL
snackcache-0.2.0.dist-info/entry_points.txt
snackcache-0.2.0.dist-info/top_level.txt
snackcache-0.2.0.dist-info/RECORD
