Metadata-Version: 2.4
Name: snackcache
Version: 0.2.0
Summary: Semantic caching proxy for LLM APIs
Author-email: Snack AI <hello@snackai.dev>
License: MIT
Project-URL: Homepage, https://github.com/sodiumsun/snackcache
Project-URL: Repository, https://github.com/sodiumsun/snackcache
Keywords: llm,openai,anthropic,cache,proxy,ai,inference,semantic
Classifier: Development Status :: 3 - Alpha
Classifier: Intended Audience :: Developers
Classifier: License :: OSI Approved :: MIT License
Classifier: Programming Language :: Python :: 3
Classifier: Programming Language :: Python :: 3.9
Classifier: Programming Language :: Python :: 3.10
Classifier: Programming Language :: Python :: 3.11
Classifier: Programming Language :: Python :: 3.12
Requires-Python: >=3.9
License-File: LICENSE
Requires-Dist: fastapi>=0.100.0
Requires-Dist: uvicorn>=0.23.0
Requires-Dist: httpx>=0.24.0
Requires-Dist: numpy>=1.21.0
Requires-Dist: sentence-transformers>=2.2.0
Requires-Dist: faiss-cpu>=1.7.0
Provides-Extra: redis
Requires-Dist: redis>=4.5.0; extra == "redis"
Provides-Extra: dev
Requires-Dist: pytest>=7.0.0; extra == "dev"
Requires-Dist: pytest-asyncio>=0.21.0; extra == "dev"
Requires-Dist: black>=23.0.0; extra == "dev"
Requires-Dist: ruff>=0.0.280; extra == "dev"
Dynamic: license-file
